NEMO_stockroom/__init__.py
NEMO_stockroom/admin.py
NEMO_stockroom/apps.py
NEMO_stockroom/customizations.py
NEMO_stockroom/forms.py
NEMO_stockroom/models.py
NEMO_stockroom/tests.py
NEMO_stockroom/urls.py
NEMO_stockroom/views.py
NEMO_stockroom/migrations/0001_initial.py
NEMO_stockroom/migrations/0002_alter_consumablerequest_date_deleted.py
NEMO_stockroom/migrations/0003_alter_consumablerequest_date_deleted.py
NEMO_stockroom/migrations/0004_alter_consumablerequest_date_deleted.py
NEMO_stockroom/migrations/0005_rename_consumablethumbnail_consumabledetails.py
NEMO_stockroom/migrations/__init__.py
NEMO_stockroom/templates/NEMO_stockroom/order_history.html
NEMO_stockroom/templates/NEMO_stockroom/stockroom.html
NEMO_stockroom/templates/NEMO_stockroom/stockroom_items.html
NEMO_stockroom/templates/NEMO_stockroom/stockroom_order.html
NEMO_stockroom/templates/NEMO_stockroom/stockroom_requests.html
NEMO_stockroom/templates/NEMO_stockroom/stockroom_withdraws.html
NEMO_stockroom/templates/NEMO_stockroom/customizations/customizations_stockroom.html
NEMO_stockroom/templates/base/navbar.html
NEMO_stockroom/templates/base/navbar_stockroom.html
NEMO_stockroom/templatetags/__init__.py
NEMO_stockroom/templatetags/stockroom_custom_tags_and_filters.py
nemo_stockroom-2.0.2.dist-info/METADATA
nemo_stockroom-2.0.2.dist-info/WHEEL
nemo_stockroom-2.0.2.dist-info/top_level.txt
nemo_stockroom-2.0.2.dist-info/RECORD
