Metadata-Version: 2.4
Name: NEMO-stockroom
Version: 2.0.2
Summary: Stockroom plugin for NEMO
Home-page: https://gitlab.com/nemo-community/upenn/nemo-stockroom-cart
Author: David J. Jones
Author-email: davijon@seas.upenn.edu
Keywords: NEMO
Requires-Dist: django
Provides-Extra: nemo-ce
Requires-Dist: NEMO-CE>=1.7.0; extra == "nemo-ce"
Provides-Extra: nemo
Requires-Dist: NEMO>=4.7.0; extra == "nemo"
Provides-Extra: dev-tools
Requires-Dist: pre-commit; extra == "dev-tools"
Requires-Dist: djlint; extra == "dev-tools"
Requires-Dist: black; extra == "dev-tools"
Dynamic: author
Dynamic: author-email
Dynamic: home-page
Dynamic: keywords
Dynamic: provides-extra
Dynamic: requires-dist
Dynamic: summary
